{"name":"Mutual Fund","version":1,"type":"json","application":"DwAR","mesh":[{"name":"image_c938f518_d34d15d8","position":[0,0.04,0.44843741786827446],"assetType":"image","rotation":[-0.001,0,0],"scale":[0.5,0.5,0.5],"assetsId":"c938f518-8157-4327-b5a9-af4208d07831","imageType":"plane","fileName":"mutual-fund-cta.png","event":{"isClickable":true,"redirectURL":"https://www.mutualfundssahihai.com/en","eventName":"Mutual Fund Website"},"meshObject":{"URL":"blob:https://dwarstudio.liberin.in/84da60f9-5fb7-4637-9494-bec6d40a721d","id":"d15d87a0-4cd5-4a29-b4b2-fbd390b58532","type":"Mesh","notIncluded":null,"shaderName":null,"name":"image_c938f518_d34d34db","assetRatio":0.21}},{"name":"target_imageundefi4025d","position":[0.01,0.01,0.01],"assetType":"image","rotation":[-0.001,0,0],"scale":[1,1,1],"imageType":"target","fileName":"mutual-fund-marker.jpg","event":{},"meshObject":{"URL":"blob:https://dwarstudio.liberin.in/a83641a1-a0d6-4ed5-8e8b-a800a8d19b88","id":"4025d0e2-1543-4833-a439-7743d0053798","type":"Mesh","notIncluded":true,"shaderName":null,"assetRatio":0.6346691519105312}},{"name":"video_asset_3ba021dccfb","position":[0,0,0],"assetType":"video","rotation":[-0.002,0,0],"scale":[1,1,1],"assetsId":"3ba021c4-65a6-44f4-910f-17ec982024f9","fileName":"mutual-funds-video.mp4","chromaEnable":false,"event":{"isClickable":true},"meshObject":{"URL":"blob:https://dwarstudio.liberin.in/1d0fd8aa-20f9-46ac-b9c8-8ae0df03904a","id":"dccfb58b-97a4-4497-83e3-34bea97c2f7d","type":"Mesh","notIncluded":null,"shaderName":null,"name":"video_asset_3ba021c08ae","assetRatio":0.5625}}]}